cogpyt/__about__.py
cogpyt/__init__.py
cogpyt/context.py
cogpyt/decorator.py
cogpyt/exception.py
test/__init__.py
test/test_context.py
test/test_decorator.py
test/test_sample.py
cogpyt-0.0.1.dist-info/LICENSE
cogpyt-0.0.1.dist-info/METADATA
cogpyt-0.0.1.dist-info/WHEEL
cogpyt-0.0.1.dist-info/top_level.txt
cogpyt-0.0.1.dist-info/RECORD
