Metadata-Version: 2.1
Name: cogpyt
Version: 0.0.1
Summary: Code Generation in (pure) Python
Home-page: https://github.com/BoyanH/cogpyt
Author: Boyan Hristov
License: MIT
Platform: UNKNOWN
Requires-Python: >=3.8
License-File: LICENSE
